app.py
sailor_remote_agent-0.1.0.dist-info/METADATA
sailor_remote_agent-0.1.0.dist-info/WHEEL
sailor_remote_agent-0.1.0.dist-info/entry_points.txt
sailor_remote_agent-0.1.0.dist-info/top_level.txt
sailor_remote_agent-0.1.0.dist-info/RECORD
