Metadata-Version: 2.4
Name: sailor-remote-agent
Version: 0.1.0
Summary: Minimal Bottle web app for clipboard and evaluation operations
Requires-Python: >=3.7
Requires-Dist: bottle>=0.12.0
